chopro_epub/__init__.py
chopro_epub/chopro-epub.css
chopro_epub/parser.py
chopro_epub/cli/__init__.py
chopro_epub/cli/epub.py
chopro_epub/cli/html.py
chopro_epub-1.1.1.dist-info/LICENSE.md
chopro_epub-1.1.1.dist-info/METADATA
chopro_epub-1.1.1.dist-info/WHEEL
chopro_epub-1.1.1.dist-info/entry_points.txt
chopro_epub-1.1.1.dist-info/top_level.txt
chopro_epub-1.1.1.dist-info/RECORD
